ensembledata/api/__init__.py
ensembledata/api/_async_client.py
ensembledata/api/_client.py
ensembledata/api/_requester.py
ensembledata/api/_response.py
ensembledata/api/_version.py
ensembledata/api/errors.py
ensembledata/api/py.typed
ensembledata-0.2.9.dist-info/licenses/LICENCE
ensembledata-0.2.9.dist-info/METADATA
ensembledata-0.2.9.dist-info/WHEEL
ensembledata-0.2.9.dist-info/top_level.txt
ensembledata-0.2.9.dist-info/RECORD
