Metadata-Version: 2.4
Name: ensembledata
Version: 0.2.9
Summary: Python bindings for the EnsembleData API
Author-email: EnsembleData <hello@ensembledata.com>, Fayd Speare <fayd@ensembledata.com>
License: LICENCE
Project-URL: Homepage, https://ensembledata.com
Project-URL: Documenation, https://ensembledata.com/apis/docs
Project-URL: Repository, https://github.com/ensembledata/ensembledata-python
Keywords: ensembledata api,tiktok api,instagram api,youtube api,reddit api
Classifier: Development Status :: 4 - Beta
Classifier: Intended Audience :: Developers
Classifier: License :: OSI Approved :: MIT License
Classifier: Operating System :: OS Independent
Classifier: Typing :: Typed
Classifier: Programming Language :: Python :: 3
Classifier: Programming Language :: Python :: 3 :: Only
Classifier: Programming Language :: Python :: 3.7
Classifier: Programming Language :: Python :: 3.8
Classifier: Programming Language :: Python :: 3.9
Classifier: Programming Language :: Python :: 3.10
Classifier: Programming Language :: Python :: 3.11
Classifier: Programming Language :: Python :: 3.12
Requires-Python: >=3.7
License-File: LICENCE
Requires-Dist: httpx
Requires-Dist: typing-extensions; python_version == "3.7"
Dynamic: license-file
